xenonpy/__doc__.py
xenonpy/__init__.py
xenonpy/__main__.py
xenonpy/_conf.py
xenonpy/conf.yml
xenonpy/contrib/README.md
xenonpy/contrib/__init__.py
xenonpy/contrib/extend_descriptors/README.md
xenonpy/contrib/extend_descriptors/__init__.py
xenonpy/contrib/extend_descriptors/descriptor/__init__.py
xenonpy/contrib/extend_descriptors/descriptor/frozen_featurizer_descriptor.py
xenonpy/contrib/extend_descriptors/descriptor/mordred_descriptor.py
xenonpy/contrib/extend_descriptors/descriptor/organic_comp_descriptor.py
xenonpy/contrib/ismd/README.md
xenonpy/contrib/ismd/__init__.py
xenonpy/contrib/ismd/reactant_pool.py
xenonpy/contrib/ismd/reactor.py
xenonpy/contrib/sample_codes/combine_fragments/combine_fragments.py
xenonpy/contrib/sample_codes/iQSPR_V/iQSPR_F.py
xenonpy/contrib/sample_codes/iQSPR_V/iQSPR_V.py
xenonpy/contrib/sample_codes/iQSPR_V/iQSPR_VF.py
xenonpy/datatools/__init__.py
xenonpy/datatools/dataset.py
xenonpy/datatools/mp_ids.txt
xenonpy/datatools/preset.py
xenonpy/datatools/splitter.py
xenonpy/datatools/transform.py
xenonpy/descriptor/__init__.py
xenonpy/descriptor/base.py
xenonpy/descriptor/cgcnn.py
xenonpy/descriptor/compositions.py
xenonpy/descriptor/fingerprint.py
xenonpy/descriptor/frozen_featurizer.py
xenonpy/descriptor/structure.py
xenonpy/inverse/__init__.py
xenonpy/inverse/base.py
xenonpy/inverse/iqspr/__init__.py
xenonpy/inverse/iqspr/estimator.py
xenonpy/inverse/iqspr/iqspr.py
xenonpy/inverse/iqspr/iqspr4df.py
xenonpy/inverse/iqspr/modifier.py
xenonpy/mdl/__init__.py
xenonpy/mdl/base.py
xenonpy/mdl/descriptor.py
xenonpy/mdl/mdl.py
xenonpy/mdl/method.py
xenonpy/mdl/model.py
xenonpy/mdl/modelset.py
xenonpy/mdl/property.py
xenonpy/model/__init__.py
xenonpy/model/cgcnn.py
xenonpy/model/extern.py
xenonpy/model/sequential.py
xenonpy/model/nn/__init__.py
xenonpy/model/nn/layer.py
xenonpy/model/nn/wrap.py
xenonpy/model/training/__init__.py
xenonpy/model/training/base.py
xenonpy/model/training/checker.py
xenonpy/model/training/clip_grad.py
xenonpy-0.6.7.dist-info/LICENSE
xenonpy-0.6.7.dist-info/METADATA
xenonpy-0.6.7.dist-info/WHEEL
xenonpy-0.6.7.dist-info/top_level.txt
xenonpy-0.6.7.dist-info/RECORD
