Metadata-Version: 2.1
Name: xenonpy
Version: 0.6.7
Summary: material descriptor library
Home-page: https://github.com/yoshida-lab/xenonpy
Author: ['TsumiNa', 'stewu5']
Author-email: liu.chang.1865@gmail.com
Maintainer: ['TsumiNa', 'stewu5']
Maintainer-email: liu.chang.1865@gmail.com
License: BSD (3-clause)
Download-URL: https://github.com/yoshida-lab/xenonpy/archive/v0.6.7.tar.gz
Platform: Windows
Platform: MacOS
Platform: Unix
Classifier: Development Status :: 4 - Beta
Classifier: Intended Audience :: Science/Research
Classifier: License :: OSI Approved :: BSD License
Classifier: Natural Language :: English
Classifier: Operating System :: Microsoft :: Windows
Classifier: Operating System :: MacOS
Classifier: Operating System :: Unix
Classifier: Programming Language :: Python :: 3.7
Classifier: Programming Language :: Python :: 3.8
Classifier: Programming Language :: Python :: 3.9
Requires-Python: ~=3.7
License-File: LICENSE
Requires-Dist: tqdm
Requires-Dist: seaborn
Requires-Dist: plotly
Requires-Dist: requests
Requires-Dist: ruamel.yaml
Requires-Dist: mordred
Requires-Dist: Deprecated
Requires-Dist: pandas (>=1.1.3)
Requires-Dist: pymatgen (>=2020.10.09)
Requires-Dist: scikit-learn (>=0.23.0)
Requires-Dist: scipy (>=1.5.0)
Requires-Dist: torch (>=1.7.0)
Requires-Dist: joblib (>=0.13.0)
